smsru/__init__.py
smsru/aioclient.py
smsru/client.py
smsru/models/__init__.py
smsru/models/base.py
smsru/models/callcheck.py
smsru/models/limits.py
smsru/models/senders.py
smsru/models/sms.py
smsru/models/stoplist.py
tests/__init__.py
tests/test_balance.py
tests/test_callcheck.py
tests/test_check_sms.py
tests/test_limits.py
tests/test_send_sms.py
tests/test_senders.py
tests/test_sms_cost.py
aiosmsru-0.2.1.dist-info/LICENSE
aiosmsru-0.2.1.dist-info/METADATA
aiosmsru-0.2.1.dist-info/WHEEL
aiosmsru-0.2.1.dist-info/top_level.txt
aiosmsru-0.2.1.dist-info/RECORD
