Metadata-Version: 2.1
Name: aiosmsru
Version: 0.2.1
Summary: (A)sync client for sms.ru with pydantic responses
Home-page: https://github.com/WhiteApfel/aiosmsru
Author: WhiteApfel
Author-email: white@pfel.ru
License: Mozilla Public License 2.0
Keywords: sms wrapper api russia
Classifier: Programming Language :: Python :: 3
Classifier: Programming Language :: Python :: 3.6
Classifier: Programming Language :: Python :: 3.7
Classifier: Programming Language :: Python :: 3.8
Classifier: Programming Language :: Python :: 3.9
Classifier: Programming Language :: Python :: 3.10
Classifier: Programming Language :: Python :: Implementation :: PyPy
Classifier: Intended Audience :: Developers
Classifier: Topic :: Software Development :: Libraries
License-File: LICENSE
Requires-Dist: httpx (~=0.23.0)
Requires-Dist: pydantic (~=1.10.2)
